libgentools/__init__.py
libgentools/libgentools.py
libgentools-0.0.1.dist-info/METADATA
libgentools-0.0.1.dist-info/WHEEL
libgentools-0.0.1.dist-info/licenses/LICENSE
libgentools-0.0.1.dist-info/RECORD
