Metadata-Version: 2.3
Name: libgentools
Version: 0.0.1
Summary: A Python library for downloading content from Library Genesis.
Project-URL: Homepage, https://github.com/gaaldvd/libgentools
Project-URL: Documentation, https://libgentools.readthedocs.io
Project-URL: Issues, https://github.com/gaaldvd/libgentools/issues
Author-email: David Gaal <gaaldavid@tuta.io>
Classifier: License :: OSI Approved :: GNU General Public License v3 (GPLv3)
Classifier: Operating System :: OS Independent
Classifier: Programming Language :: Python :: 3
Requires-Python: >=3.12
